airo_spatial_algebra/__init__.py
airo_spatial_algebra/operations.py
airo_spatial_algebra/py.typed
airo_spatial_algebra/se3.py
airo_spatial_algebra-2026.1.0.dist-info/METADATA
airo_spatial_algebra-2026.1.0.dist-info/WHEEL
airo_spatial_algebra-2026.1.0.dist-info/top_level.txt
airo_spatial_algebra-2026.1.0.dist-info/RECORD
