Metadata-Version: 2.4
Name: airo_spatial_algebra
Version: 2026.1.0
Summary: Code for working with SE3 poses, transforms... for robotic manipulation at the Ghent University AI and Robotics Lab
Author: Thomas Lips
Author-email: thomas.lips@ugent.be
Requires-Dist: numpy>=2.0
Requires-Dist: scipy
Requires-Dist: spatialmath-python
Requires-Dist: airo-typing>=2026.01.0
Dynamic: author
Dynamic: author-email
Dynamic: requires-dist
Dynamic: summary
